ixnetwork/__init__.py
ixnetwork/ixn_app.py
ixnetwork/ixn_hw.py
ixnetwork/ixn_interface.py
ixnetwork/ixn_object.py
ixnetwork/ixn_port.py
ixnetwork/ixn_protocol.py
ixnetwork/ixn_protocol_stack.py
ixnetwork/ixn_root.py
ixnetwork/ixn_statistics_view.py
ixnetwork/ixn_topology.py
ixnetwork/ixn_traffic.py
ixnetwork/api/__init__.py
ixnetwork/api/ixn_rest.py
ixnetwork/api/ixn_tcl.py
ixnetwork/samples/__init__.py
ixnetwork/samples/ixn_samples.py
ixnetwork/samples/test_config_classic.ixncfg
pyixnetwork-3.2.0.dist-info/METADATA
pyixnetwork-3.2.0.dist-info/WHEEL
pyixnetwork-3.2.0.dist-info/top_level.txt
pyixnetwork-3.2.0.dist-info/RECORD
