Metadata-Version: 2.1
Name: pyixnetwork
Version: 3.2.0
Summary: Python OO API package to manage Ixia IxNetwork traffic generator
Home-page: https://github.com/shmir/PyIxNetwork
Author: Yoram Shamir
Author-email: yoram@ignissoft.com
License: Apache Software License
Keywords: keysight,ixia,ixnetwork,l2l3,ixload,l4l7,tg,traffic generator,test automation,automation api
Classifier: Development Status :: 5 - Production/Stable
Classifier: Natural Language :: English
Classifier: License :: OSI Approved :: Apache Software License
Classifier: Intended Audience :: Developers
Classifier: Operating System :: OS Independent
Classifier: Topic :: Software Development :: Testing
Classifier: Programming Language :: Python :: 3.7
Classifier: Programming Language :: Python :: 3.8
Classifier: Programming Language :: Python :: 3.9
Classifier: Programming Language :: Python :: 3.10
Requires-Dist: requests
Requires-Dist: pytrafficgen (<3.2.0,>=3.1.0)
